<xml>
<names>
<name>Julianna Martinez Ruiz</name>
<name>Julianna Martinez</name>
<name>Jule Martinez</name>
<name>Julianna Ruiz</name>
<name>Jule Ruiz</name>
<name>Jule Martinez Ruiz</name>
</names>
<sort_name>Martinez</sort_name>

<position>Research Facilitator</position>
<program>Computer Science</program>
<school>University of Florida</school>
<email>juliannamartinez@ufl.edu</email>
<bio>
Julianna Martinez Ruiz is a Research Facilitator in the Department of Computer &amp; Information Science &amp; Engineering at the University of Florida. She holds a B.A. degree in Education from the University of Puerto Rico, Cayey Campus, and a teaching certificate from the Puerto Rico Department of Education. She works as an ESOL paraprofessional and a freelance illustrator. Currently, Julianna is part of the FLECKS project, assisting in the design of the system’s agents and providing classroom study support.
</bio>
<degrees>
<degree>
<abbrev>B.A.</abbrev>
<subject>Education, English as a Second Language</subject>
<graduation>2014</graduation>
<school>University of Puerto Rico, Cayey Campus</school>
</degree>
</degrees>
</xml>
